LICENSE.txt
MANIFEST.in
README.rst
setup.py
ctutils/__init__.py
ctutils/configparser.py
ctutils/ctagg.py
ctutils/ctinfo.py
ctutils/readers.py
ctutils/terminal.py
ctutils.egg-info/PKG-INFO
ctutils.egg-info/SOURCES.txt
ctutils.egg-info/dependency_links.txt
ctutils.egg-info/entry_points.txt
ctutils.egg-info/requires.txt
ctutils.egg-info/top_level.txt
ctutils/windows/__init__.py
ctutils/windows/main_window.py