Metadata-Version: 1.1
Name: ctutils
Version: 0.3
Summary: Tools for analyzing data in CT scans
Home-page: http://ctutils.readthedocs.org/
Author: Dave Hughes
Author-email: dave@waveform.org.uk
License: GNU General Public License v3 or later (GPLv3+)
Keywords: ct,tomography
Platform: A
Platform: L
Platform: L
Classifier: Development Status :: 4 - Beta
Classifier: Intended Audience :: Science/Research
Classifier: License :: OSI Approved :: GNU General Public License v3 or later (GPLv3+)
Classifier: Operating System :: Unix
Classifier: Operating System :: Microsoft :: Windows
Classifier: Programming Language :: Python :: 2.7
Classifier: Programming Language :: Python :: 3
Classifier: Topic :: Scientific/Engineering :: Visualization
